{"KRW-WAVES": [1321.76, 0, null, null, null, null, null, null, null, null, null, null], "KRW-ETH": [1321.91, 0, null, null, null, null, null, null, null, null, null, null], "KRW-XRP": [1321.76, 0, null, null, null, null, null, null, null, null, null, null], "KRW-SAND": [1320.11, 0, null, null, null, null, null, null, null, null, null, null], "KRW-SOL": [1322.57, 0, null, null, null, null, null, null, null, null, null, null], "KRW-APT": [1322.57, 0, null, null, null, null, null, null, null, null, null, null], "KRW-ETC": [1321.76, 0, null, null, null, null, null, null, null, null, null, null], "KRW-GMT": [1322.29, 0, null, null, null, null, null, null, null, null, null, null]}